{
  "items": [
    {
      "cart_item_id": "cart_VW9Yu-RSd2ZYpdpFS9sj",
      "item_id": "item_x9IKeDcJ1QCZqquElmvp",
      "quantity": 1,
      "selected_customizations": {},
      "added_at": "2025-12-12T22:26:24.012Z"
    },
    {
      "cart_item_id": "cart_3pxYgsHij9Ec_sthAS8H",
      "item_id": "item_x9IKeDcJ1QCZqquElmvp",
      "quantity": 1,
      "selected_customizations": {},
      "added_at": "2025-12-12T22:28:29.648Z"
    },
    {
      "cart_item_id": "cart_OQxW9UgHafaBjpzsCx6V",
      "item_id": "item_x9IKeDcJ1QCZqquElmvp",
      "quantity": 1,
      "selected_customizations": {},
      "added_at": "2025-12-12T22:31:48.808Z"
    },
    {
      "cart_item_id": "cart_8xMB8thTzzKxay1euJZ_",
      "item_id": "item_krSsB_0CBiVwMgnbTUod",
      "quantity": 1,
      "selected_customizations": {},
      "added_at": "2025-12-12T22:34:11.568Z"
    },
    {
      "cart_item_id": "cart_JKSEh5r324iJsB97f50a",
      "item_id": "item_x9IKeDcJ1QCZqquElmvp",
      "quantity": 1,
      "selected_customizations": {},
      "added_at": "2025-12-12T22:50:25.439Z"
    },
    {
      "cart_item_id": "cart_KkkJUUw_JpjQRDDYspap",
      "item_id": "item__q8rNhlgVELwMWK6pZlJ",
      "quantity": 1,
      "selected_customizations": {},
      "added_at": "2025-12-12T22:52:12.386Z"
    },
    {
      "cart_item_id": "cart_FpMna8MCm4f7ARQfNMQG",
      "item_id": "item_x9IKeDcJ1QCZqquElmvp",
      "quantity": 1,
      "selected_customizations": {},
      "added_at": "2025-12-12T22:53:55.068Z"
    },
    {
      "cart_item_id": "cart_Rdvz0WQHAkVtg52ugxLT",
      "item_id": "item_x9IKeDcJ1QCZqquElmvp",
      "quantity": 1,
      "selected_customizations": {},
      "added_at": "2025-12-12T22:55:27.182Z"
    }
  ],
  "discount_code": null,
  "updated_at": "2025-12-12T22:55:27.182Z"
}